redis_timeseries_manager/__init__.py
redis_timeseries_manager/redis_timeseries_manager.py
redis_timeseries_manager-2.3.dist-info/LICENSE
redis_timeseries_manager-2.3.dist-info/METADATA
redis_timeseries_manager-2.3.dist-info/WHEEL
redis_timeseries_manager-2.3.dist-info/top_level.txt
redis_timeseries_manager-2.3.dist-info/RECORD
