Metadata-Version: 2.1
Name: redis-timeseries-manager
Version: 2.3
Summary: RedisTimeseriesManager is a redis timeseries management system that enhance redis timeseries with features including multi-line data, built-in timeframes, data classifiers and convenient data accessors.
Home-page: https://github.com/ahmadazizi/redis_timeseries_manager
Author: Ahmad Azizi
Author-email: activepost@gmail.com
Project-URL: Bug Tracker, https://github.com/ahmadazizi/redis_timeseries_manager/issues
Classifier: Programming Language :: Python :: 3
Classifier: License :: OSI Approved :: MIT License
Classifier: Operating System :: OS Independent
Requires-Python: >=3.6
License-File: LICENSE
Requires-Dist: redis >=4.0
Requires-Dist: pandas >=1
